pacfix/__init__.py
pacfix/__main__.py
pacfix/debug.py
pacfix/invariant.py
pacfix/synthesis.py
pacfix/utils.py
pacfix-0.0.4.dist-info/entry_points.txt
pacfix-0.0.4.dist-info/licenses/LICENSE
pacfix-0.0.4.dist-info/WHEEL
pacfix-0.0.4.dist-info/METADATA
pacfix-0.0.4.dist-info/RECORD
