Metadata-Version: 2.4
Name: pacfix
Version: 0.0.4
Summary: PAC-learning-based program systhesizer
Keywords: apr
Author-email: Seungheon Han <shhan@unist.ac.kr>
Maintainer-email: Seungheon Han <shhan@unist.ac.kr>
Requires-Python: >=3.6
Classifier: Development Status :: 1 - Planning
Classifier: Environment :: Console
Classifier: License :: OSI Approved :: MIT License
Classifier: Operating System :: OS Independent
Classifier: Programming Language :: Python
License-File: LICENSE
Requires-Dist: pysmt
Project-URL: GitHub, https://github.com/hsh814/pacfix-python
